Assignment 2/ram.vhd
library ieee;
use ieee.std_logic_1164.all;
use ieee.numeric_std.all;

entity ram is
    port (
        clk :in std_logic;
        w   :in std_logic;
        din :in std_logic_vector(15 downto 0);
        addr:in std_logic_vector(9 downto 0);
        dout:out std_logic_vector(15 downto 0));
end entity;

architecture beh of ram is
    type mem_array is array (0 to 1023) of std_logic_vector(15 downto 0);
    signal ra_mem:mem_array:=(others => X"0000");
begin
    dout <= ra_mem(to_integer(unsigned(addr)));
    process(clk)
    begin
        if rising_edge(clk) then
            if w='1' then
                ra_mem(to_integer(unsigned(addr))) <= din;
            end if;
        end if;
    end process;
end beh;

Assignment 2/ramtb.vhd
library ieee;
use ieee.std_logic_1164.all;

entity tb_ram is
end tb_ram;

architecture tb of tb_ram is

    component ram
        port (clk  : in std_logic;
              w    : in std_logic;
              din  : in std_logic_vector (15 downto 0);
              addr : in std_logic_vector (9 downto 0);
              dout : out std_logic_vector (15 downto 0));
    end component;

    signal clk  : std_logic;
    signal w    : std_logic;
    signal din  : std_logic_vector (15 downto 0);
    signal addr : std_logic_vector (9 downto 0);
    signal dout : std_logic_vector (15 downto 0);

    constant TbPeriod : time := 50 ns; -- EDIT Put right period here
    signal TbClock : std_logic := '0';
    signal TbSimEnded : std_logic := '0';

begin

    dut : ram
    port map (clk  => clk,
              w    => w,
              din  => din,
              addr => addr,
              dout => dout);

    -- Clock generation
    TbClock <= not TbClock after TbPeriod/2 when TbSimEnded /= '1' else '0';

    -- EDIT: Check that clk is really your main clock signal
    clk <= TbClock;

    stimuli : process
    begin
        -- EDIT Adapt initialization as needed
        w <= '0';
        din <= (others => '0');
        addr <= (others => '0');
        wait for 100 ns;
        w <= '1';
        addr <= "0000000101";
        din <= x"1010";
        wait for 100 ns;
        addr <= "0000000001";
        din <= x"f010";
        w <= '0';
        wait for 100 ns;
        addr <= "0000000101";
        wait for 100 ns;
        addr <= "0000000001";

        wait for 100 * TbPeriod;

        -- Stop the clock and hence terminate the simulation
        TbSimEnded <= '1';
        wait;
    end process;

end tb;

-- Configuration block below is required by some simulators. Usually no need to edit.

--configuration cfg_tb_ram of tb_ram is
--    for tb
--    end for;
--end cfg_tb_ram;

Assignment 2/wave.vcd
$date
  Thu Sep 15 16:22:32 2022
$end
$version
  GHDL v0
$end
$timescale
  1 fs
$end
$scope module standard $end
$upscope $end
$scope module std_logic_1164 $end
$upscope $end
$scope module numeric_std $end
$upscope $end
$scope module tb_ram $end
$var reg 1 ! clk $end
$var reg 1 " w $end
$var reg 16 # din[15:0] $end
$var reg 10 $ addr[9:0] $end
$var reg 16 % dout[15:0] $end
$var reg 1 & tbclock $end
$var reg 1 ' tbsimended $end
$scope module dut $end
$var reg 1 ( clk $end
$var reg 1 ) w $end
$var reg 16 * din[15:0] $end
$var reg 10 + addr[9:0] $end
$var reg 16 , dout[15:0] $end
$comment ra_mem is not handled $end
$upscope $end
$upscope $end
$enddefinitions $end
#0
0!
0"
b0000000000000000 #
b0000000000 $
bUUUUUUUUUUUUUUUU %
0&
0'
0(
0)
b0000000000000000 *
b0000000000 +
bUUUUUUUUUUUUUUUU ,
#25000000
1!
b0000000000000000 %
1&
1(
b0000000000000000 ,
#50000000
0!
0&
0(
#75000000
1!
1&
1(
#100000000
0!
1"
b0001000000010000 #
b0000000101 $
0&
0(
1)
b0001000000010000 *
b0000000101 +
#125000000
1!
1&
1(
#150000000
0!
0&
0(
#175000000
1!
b0001000000010000 %
1&
1(
b0001000000010000 ,
#200000000
0!
0"
b1111000000010000 #
b0000000001 $
0&
0(
0)
b1111000000010000 *
b0000000001 +
#225000000
1!
b0000000000000000 %
1&
1(
b0000000000000000 ,
#250000000
0!
0&
0(
#275000000
1!
1&
1(
#300000000
0!
b0000000101 $
0&
0(
b0000000101 +
#325000000
1!
b0001000000010000 %
1&
1(
b0001000000010000 ,
#350000000
0!
0&
0(
#375000000
1!
1&
1(
#400000000
0!
b0000000001 $
0&
0(
b0000000001 +
#425000000
1!
b0000000000000000 %
1&
1(
b0000000000000000 ,
